{
  "repo": "tailwindlabs/tailwindcss",
  "lookback_days": 90,
  "window_days": 14,
  "total_prs": 133,
  "classifiable_prs": 117,
  "pending_prs": 11,
  "machine_catch_rate": 0.2051,
  "human_save_rate": 0.7949,
  "escape_rate": 0.0,
  "ungated_prs": 5,
  "discard_rate": null,
  "prs": [
    {
      "number": 19851,
      "title": "Small refactor of canonicalization tests",
      "classification": "pending",
      "ci_status": "clean_pass",
      "review_modified": false,
      "escaped": false,
      "escape_reason": "",
      "escape_confidence": null,
      "merged_at": "2026-03-25T14:18:14+00:00",
      "review_cycles": 0,
      "time_to_merge_hours": 0.1,
      "lines_changed": 712,
      "size_bucket": "large"
    },
    {
      "number": 19849,
      "title": "Add more canonicalization rules for deprecated utilities",
      "classification": "pending",
      "ci_status": "clean_pass",
      "review_modified": false,
      "escaped": false,
      "escape_reason": "",
      "escape_confidence": null,
      "merged_at": "2026-03-25T10:38:28+00:00",
      "review_cycles": 0,
      "time_to_merge_hours": 0.1,
      "lines_changed": 157,
      "size_bucket": "medium"
    },
    {
      "number": 19846,
      "title": "Make upgrade tooling more stable",
      "classification": "pending",
      "ci_status": "clean_pass",
      "review_modified": false,
      "escaped": false,
      "escape_reason": "",
      "escape_confidence": null,
      "merged_at": "2026-03-24T16:24:13+00:00",
      "review_cycles": 0,
      "time_to_merge_hours": 4.3,
      "lines_changed": 536,
      "size_bucket": "large"
    },
    {
      "number": 19843,
      "title": "Use `--placeholder-color` instead of `--background-color` for `placeholder-*` utilities",
      "classification": "pending",
      "ci_status": "clean_pass",
      "review_modified": false,
      "escaped": false,
      "escape_reason": "",
      "escape_confidence": null,
      "merged_at": "2026-03-23T14:57:20+00:00",
      "review_cycles": 0,
      "time_to_merge_hours": 0.1,
      "lines_changed": 3,
      "size_bucket": "small"
    },
    {
      "number": 19842,
      "title": "Collapse more utilities by expanding their declarations",
      "classification": "pending",
      "ci_status": "clean_pass",
      "review_modified": false,
      "escaped": false,
      "escape_reason": "",
      "escape_confidence": null,
      "merged_at": "2026-03-23T14:33:44+00:00",
      "review_cycles": 0,
      "time_to_merge_hours": 0.4,
      "lines_changed": 516,
      "size_bucket": "large"
    },
    {
      "number": 19837,
      "title": "fix(canonicalize): collapse arbitrary values into shorthand utilities",
      "classification": "pending",
      "ci_status": "clean_pass",
      "review_modified": false,
      "escaped": false,
      "escape_reason": "",
      "escape_confidence": null,
      "merged_at": "2026-03-23T10:32:25+00:00",
      "review_cycles": 0,
      "time_to_merge_hours": 33.9,
      "lines_changed": 37,
      "size_bucket": "small"
    },
    {
      "number": 19829,
      "title": "Fix crash due to invalid characters in candidate",
      "classification": "pending",
      "ci_status": "clean_pass",
      "review_modified": false,
      "escaped": false,
      "escape_reason": "",
      "escape_confidence": null,
      "merged_at": "2026-03-20T13:51:37+00:00",
      "review_cycles": 0,
      "time_to_merge_hours": 1.2,
      "lines_changed": 41,
      "size_bucket": "small"
    },
    {
      "number": 19827,
      "title": "Add canonicalizations for `tracking-*` utilities",
      "classification": "machine_catch",
      "ci_status": "clean_pass",
      "review_modified": false,
      "escaped": false,
      "escape_reason": "",
      "escape_confidence": null,
      "merged_at": "2026-03-19T18:53:16+00:00",
      "review_cycles": 0,
      "time_to_merge_hours": 0.7,
      "lines_changed": 94,
      "size_bucket": "small"
    },
    {
      "number": 19821,
      "title": "4.2.2",
      "classification": "human_save",
      "ci_status": "clean_pass",
      "review_modified": true,
      "escaped": false,
      "escape_reason": "",
      "escape_confidence": null,
      "merged_at": "2026-03-18T15:44:08+00:00",
      "review_cycles": 0,
      "time_to_merge_hours": 0.7,
      "lines_changed": 57,
      "size_bucket": "small"
    },
    {
      "number": 19812,
      "title": "Fix canonicalization resulting in empty list",
      "classification": "machine_catch",
      "ci_status": "clean_pass",
      "review_modified": false,
      "escaped": false,
      "escape_reason": "",
      "escape_confidence": null,
      "merged_at": "2026-03-17T12:00:31+00:00",
      "review_cycles": 0,
      "time_to_merge_hours": 0.2,
      "lines_changed": 23,
      "size_bucket": "small"
    },
    {
      "number": 19809,
      "title": "Improve canonicalization for bare values exceeding default spacing scale suggestions",
      "classification": "machine_catch",
      "ci_status": "clean_pass",
      "review_modified": false,
      "escaped": false,
      "escape_reason": "",
      "escape_confidence": null,
      "merged_at": "2026-03-16T21:44:29+00:00",
      "review_cycles": 0,
      "time_to_merge_hours": 0.3,
      "lines_changed": 56,
      "size_bucket": "small"
    },
    {
      "number": 19804,
      "title": "Cleanup inconsistencies related to (regex) escapes",
      "classification": "machine_catch",
      "ci_status": "clean_pass",
      "review_modified": false,
      "escaped": false,
      "escape_reason": "",
      "escape_confidence": null,
      "merged_at": "2026-03-15T21:04:58+00:00",
      "review_cycles": 0,
      "time_to_merge_hours": 0.1,
      "lines_changed": 38,
      "size_bucket": "small"
    },
    {
      "number": 19803,
      "title": "fix(vite): resolve tsconfig paths in CSS and JS resolvers",
      "classification": "pending",
      "ci_status": "clean_pass",
      "review_modified": false,
      "escaped": false,
      "escape_reason": "",
      "escape_confidence": null,
      "merged_at": "2026-03-20T15:19:18+00:00",
      "review_cycles": 0,
      "time_to_merge_hours": 125.8,
      "lines_changed": 182,
      "size_bucket": "medium"
    },
    {
      "number": 19797,
      "title": "fix: remove unused braces dependencies",
      "classification": "human_save",
      "ci_status": "clean_pass",
      "review_modified": true,
      "escaped": false,
      "escape_reason": "",
      "escape_confidence": null,
      "merged_at": "2026-03-15T21:10:54+00:00",
      "review_cycles": 0,
      "time_to_merge_hours": 38.1,
      "lines_changed": 13,
      "size_bucket": "small"
    },
    {
      "number": 19796,
      "title": "Add `--stream` flag to `canonicalize` subcommand",
      "classification": "human_save",
      "ci_status": "clean_pass",
      "review_modified": true,
      "escaped": false,
      "escape_reason": "",
      "escape_confidence": null,
      "merged_at": "2026-03-16T15:00:12+00:00",
      "review_cycles": 0,
      "time_to_merge_hours": 58.2,
      "lines_changed": 196,
      "size_bucket": "medium"
    },
    {
      "number": 19790,
      "title": "Add support for Vite 8 in `@tailwindcss/vite`",
      "classification": "machine_catch",
      "ci_status": "clean_pass",
      "review_modified": false,
      "escaped": false,
      "escape_reason": "",
      "escape_confidence": null,
      "merged_at": "2026-03-12T19:54:34+00:00",
      "review_cycles": 0,
      "time_to_merge_hours": 0.6,
      "lines_changed": 589,
      "size_bucket": "large"
    },
    {
      "number": 19788,
      "title": "Fix internal source map warnings",
      "classification": "machine_catch",
      "ci_status": "clean_pass",
      "review_modified": false,
      "escaped": false,
      "escape_reason": "",
      "escape_confidence": null,
      "merged_at": "2026-03-12T11:21:00+00:00",
      "review_cycles": 0,
      "time_to_merge_hours": 0.4,
      "lines_changed": 10,
      "size_bucket": "small"
    },
    {
      "number": 19783,
      "title": "Add `tailwindcss canonicalize` sub-command",
      "classification": "machine_catch",
      "ci_status": "failed",
      "review_modified": false,
      "escaped": false,
      "escape_reason": "",
      "escape_confidence": null,
      "merged_at": "2026-03-11T19:30:22+00:00",
      "review_cycles": 0,
      "time_to_merge_hours": 0.1,
      "lines_changed": 568,
      "size_bucket": "large"
    },
    {
      "number": 19769,
      "title": "Canonicalize `calc(var(--spacing)*\u2026)` expressions into `--spacing(\u2026)`",
      "classification": "machine_catch",
      "ci_status": "clean_pass",
      "review_modified": false,
      "escaped": false,
      "escape_reason": "",
      "escape_confidence": null,
      "merged_at": "2026-03-08T19:19:35+00:00",
      "review_cycles": 0,
      "time_to_merge_hours": 25.2,
      "lines_changed": 79,
      "size_bucket": "small"
    },
    {
      "number": 19745,
      "title": "fix(vite): skip full reload for server only modules scanned by client css",
      "classification": "human_save",
      "ci_status": "clean_pass",
      "review_modified": true,
      "escaped": false,
      "escape_reason": "",
      "escape_confidence": null,
      "merged_at": "2026-03-12T18:49:41+00:00",
      "review_cycles": 0,
      "time_to_merge_hours": 250.1,
      "lines_changed": 112,
      "size_bucket": "medium"
    },
    {
      "number": 19730,
      "title": "Extract classes from interpolated expressions in Ruby",
      "classification": "machine_catch",
      "ci_status": "clean_pass",
      "review_modified": false,
      "escaped": false,
      "escape_reason": "",
      "escape_confidence": null,
      "merged_at": "2026-02-26T11:23:50+00:00",
      "review_cycles": 0,
      "time_to_merge_hours": 0.1,
      "lines_changed": 18,
      "size_bucket": "small"
    },
    {
      "number": 19727,
      "title": "fix(canonicalize): handle utilities with empty property maps in collapse",
      "classification": "human_save",
      "ci_status": "failed",
      "review_modified": true,
      "escaped": false,
      "escape_reason": "",
      "escape_confidence": null,
      "merged_at": "2026-03-10T15:48:07+00:00",
      "review_cycles": 0,
      "time_to_merge_hours": 303.4,
      "lines_changed": 40,
      "size_bucket": "small"
    },
    {
      "number": 19725,
      "title": "Guard object lookups against inherited prototype properties",
      "classification": "human_save",
      "ci_status": "clean_pass",
      "review_modified": true,
      "escaped": false,
      "escape_reason": "",
      "escape_confidence": null,
      "merged_at": "2026-02-25T15:16:09+00:00",
      "review_cycles": 0,
      "time_to_merge_hours": 0.5,
      "lines_changed": 90,
      "size_bucket": "small"
    },
    {
      "number": 19723,
      "title": "Fix webpack loader cache key for resource queries",
      "classification": "pending",
      "ci_status": "clean_pass",
      "review_modified": false,
      "escaped": false,
      "escape_reason": "",
      "escape_confidence": null,
      "merged_at": "2026-03-20T16:34:11+00:00",
      "review_cycles": 0,
      "time_to_merge_hours": 561.8,
      "lines_changed": 89,
      "size_bucket": "small"
    },
    {
      "number": 19714,
      "title": "4.2.1",
      "classification": "machine_catch",
      "ci_status": "clean_pass",
      "review_modified": false,
      "escaped": false,
      "escape_reason": "",
      "escape_confidence": null,
      "merged_at": "2026-02-23T10:45:12+00:00",
      "review_cycles": 0,
      "time_to_merge_hours": 0.1,
      "lines_changed": 51,
      "size_bucket": "small"
    },
    {
      "number": 19711,
      "title": "Fix missing extracted classes in mdx files",
      "classification": "machine_catch",
      "ci_status": "clean_pass",
      "review_modified": false,
      "escaped": false,
      "escape_reason": "",
      "escape_confidence": null,
      "merged_at": "2026-02-22T12:02:05+00:00",
      "review_cycles": 0,
      "time_to_merge_hours": 11.6,
      "lines_changed": 23,
      "size_bucket": "small"
    },
    {
      "number": 19700,
      "title": "Correct CHANGELOG to mention inset not inline",
      "classification": "ungated",
      "ci_status": "no_checks",
      "review_modified": false,
      "escaped": false,
      "escape_reason": "",
      "escape_confidence": null,
      "merged_at": "2026-02-19T13:05:38+00:00",
      "review_cycles": 0,
      "time_to_merge_hours": 10.6,
      "lines_changed": 2,
      "size_bucket": "small"
    },
    {
      "number": 19696,
      "title": "Allow trailing dash in functional utility names",
      "classification": "human_save",
      "ci_status": "clean_pass",
      "review_modified": true,
      "escaped": false,
      "escape_reason": "",
      "escape_confidence": null,
      "merged_at": "2026-02-19T14:40:38+00:00",
      "review_cycles": 0,
      "time_to_merge_hours": 21.9,
      "lines_changed": 59,
      "size_bucket": "small"
    },
    {
      "number": 19695,
      "title": "4.2.0",
      "classification": "machine_catch",
      "ci_status": "clean_pass",
      "review_modified": false,
      "escaped": false,
      "escape_reason": "",
      "escape_confidence": null,
      "merged_at": "2026-02-18T14:45:07+00:00",
      "review_cycles": 0,
      "time_to_merge_hours": 0.9,
      "lines_changed": 85,
      "size_bucket": "small"
    },
    {
      "number": 19692,
      "title": "docs: update package README CI badge to main",
      "classification": "human_save",
      "ci_status": "clean_pass",
      "review_modified": true,
      "escaped": false,
      "escape_reason": "",
      "escape_confidence": null,
      "merged_at": "2026-02-18T10:52:07+00:00",
      "review_cycles": 0,
      "time_to_merge_hours": 4.8,
      "lines_changed": 14,
      "size_bucket": "small"
    },
    {
      "number": 19688,
      "title": "Allow multiples of `.25` in `aspect-*` fractions",
      "classification": "machine_catch",
      "ci_status": "clean_pass",
      "review_modified": false,
      "escaped": false,
      "escape_reason": "",
      "escape_confidence": null,
      "merged_at": "2026-02-17T18:32:31+00:00",
      "review_cycles": 0,
      "time_to_merge_hours": 1.0,
      "lines_changed": 10,
      "size_bucket": "small"
    },
    {
      "number": 19687,
      "title": "Add '.jj' to ignored content directories",
      "classification": "human_save",
      "ci_status": "clean_pass",
      "review_modified": true,
      "escaped": false,
      "escape_reason": "",
      "escape_confidence": null,
      "merged_at": "2026-02-17T17:09:59+00:00",
      "review_cycles": 0,
      "time_to_merge_hours": 4.4,
      "lines_changed": 18,
      "size_bucket": "small"
    },
    {
      "number": 19686,
      "title": "docs: fix GitHub links to tailwindlabs org",
      "classification": "human_save",
      "ci_status": "clean_pass",
      "review_modified": true,
      "escaped": false,
      "escape_reason": "",
      "escape_confidence": null,
      "merged_at": "2026-02-17T12:06:49+00:00",
      "review_cycles": 0,
      "time_to_merge_hours": 0.2,
      "lines_changed": 10,
      "size_bucket": "small"
    },
    {
      "number": 19679,
      "title": "Fallback to `config.createResolver` for `client` and `ssr` environments in `@tailwindcss/vite`",
      "classification": "human_save",
      "ci_status": "clean_pass",
      "review_modified": true,
      "escaped": false,
      "escape_reason": "",
      "escape_confidence": null,
      "merged_at": "2026-02-17T19:59:57+00:00",
      "review_cycles": 0,
      "time_to_merge_hours": 57.9,
      "lines_changed": 113,
      "size_bucket": "medium"
    },
    {
      "number": 19675,
      "title": "fix(canonicalize): prevent collapse cache pollution across calls",
      "classification": "human_save",
      "ci_status": "clean_pass",
      "review_modified": true,
      "escaped": false,
      "escape_reason": "",
      "escape_confidence": null,
      "merged_at": "2026-02-18T12:16:59+00:00",
      "review_cycles": 0,
      "time_to_merge_hours": 93.4,
      "lines_changed": 48,
      "size_bucket": "small"
    },
    {
      "number": 19670,
      "title": "fix: restore full page reload for watched external files on Vite 7.1+",
      "classification": "human_save",
      "ci_status": "failed",
      "review_modified": true,
      "escaped": false,
      "escape_reason": "",
      "escape_confidence": null,
      "merged_at": "2026-02-17T19:04:17+00:00",
      "review_cycles": 1,
      "time_to_merge_hours": 113.8,
      "lines_changed": 227,
      "size_bucket": "medium"
    },
    {
      "number": 19652,
      "title": "Fix/misc docs and tests",
      "classification": "human_save",
      "ci_status": "clean_pass",
      "review_modified": true,
      "escaped": false,
      "escape_reason": "",
      "escape_confidence": null,
      "merged_at": "2026-02-18T12:23:49+00:00",
      "review_cycles": 0,
      "time_to_merge_hours": 217.1,
      "lines_changed": 6,
      "size_bucket": "small"
    },
    {
      "number": 19644,
      "title": "Fix Tailwind CSS package README GitHub links",
      "classification": "human_save",
      "ci_status": "clean_pass",
      "review_modified": true,
      "escaped": false,
      "escape_reason": "",
      "escape_confidence": null,
      "merged_at": "2026-02-08T00:26:38+00:00",
      "review_cycles": 0,
      "time_to_merge_hours": 16.1,
      "lines_changed": 56,
      "size_bucket": "small"
    },
    {
      "number": 19641,
      "title": "Fix README links to use main branch",
      "classification": "human_save",
      "ci_status": "clean_pass",
      "review_modified": true,
      "escaped": false,
      "escape_reason": "",
      "escape_confidence": null,
      "merged_at": "2026-02-06T15:51:07+00:00",
      "review_cycles": 0,
      "time_to_merge_hours": 5.2,
      "lines_changed": 4,
      "size_bucket": "small"
    },
    {
      "number": 19638,
      "title": "Fix README license badge link",
      "classification": "ungated",
      "ci_status": "no_checks",
      "review_modified": false,
      "escaped": false,
      "escape_reason": "",
      "escape_confidence": null,
      "merged_at": "2026-02-05T15:59:10+00:00",
      "review_cycles": 0,
      "time_to_merge_hours": 0.4,
      "lines_changed": 2,
      "size_bucket": "small"
    },
    {
      "number": 19633,
      "title": "Fix infinite loop when using `@variant` inside `@custom-variant` that points to another `@custom-variant`",
      "classification": "machine_catch",
      "ci_status": "clean_pass",
      "review_modified": false,
      "escaped": false,
      "escape_reason": "",
      "escape_confidence": null,
      "merged_at": "2026-02-02T13:42:31+00:00",
      "review_cycles": 0,
      "time_to_merge_hours": 1.4,
      "lines_changed": 94,
      "size_bucket": "small"
    },
    {
      "number": 19632,
      "title": "Improve performance in bigger projects",
      "classification": "machine_catch",
      "ci_status": "clean_pass",
      "review_modified": false,
      "escaped": false,
      "escape_reason": "",
      "escape_confidence": null,
      "merged_at": "2026-02-17T19:15:21+00:00",
      "review_cycles": 0,
      "time_to_merge_hours": 367.8,
      "lines_changed": 1058,
      "size_bucket": "large"
    },
    {
      "number": 19627,
      "title": "Add mauve, olive, mist, and taupe color palettes",
      "classification": "human_save",
      "ci_status": "clean_pass",
      "review_modified": true,
      "escaped": false,
      "escape_reason": "",
      "escape_confidence": null,
      "merged_at": "2026-02-18T10:52:35+00:00",
      "review_cycles": 0,
      "time_to_merge_hours": 428.9,
      "lines_changed": 107,
      "size_bucket": "medium"
    },
    {
      "number": 19626,
      "title": "feat: handle backslash in `@utility` name",
      "classification": "human_save",
      "ci_status": "clean_pass",
      "review_modified": true,
      "escaped": false,
      "escape_reason": "",
      "escape_confidence": null,
      "merged_at": "2026-02-17T21:12:20+00:00",
      "review_cycles": 0,
      "time_to_merge_hours": 431.5,
      "lines_changed": 33,
      "size_bucket": "small"
    },
    {
      "number": 19625,
      "title": "Simplify logical sizing utility theme namespaces",
      "classification": "machine_catch",
      "ci_status": "clean_pass",
      "review_modified": false,
      "escaped": false,
      "escape_reason": "",
      "escape_confidence": null,
      "merged_at": "2026-01-30T15:40:51+00:00",
      "review_cycles": 0,
      "time_to_merge_hours": 0.6,
      "lines_changed": 18,
      "size_bucket": "small"
    },
    {
      "number": 19623,
      "title": "Add `font-features-*` utility for font-feature-settings",
      "classification": "human_save",
      "ci_status": "clean_pass",
      "review_modified": true,
      "escaped": false,
      "escape_reason": "",
      "escape_confidence": null,
      "merged_at": "2026-01-30T14:21:16+00:00",
      "review_cycles": 0,
      "time_to_merge_hours": 2.6,
      "lines_changed": 61,
      "size_bucket": "small"
    },
    {
      "number": 19614,
      "title": "Improve walk performance",
      "classification": "machine_catch",
      "ci_status": "clean_pass",
      "review_modified": false,
      "escaped": false,
      "escape_reason": "",
      "escape_confidence": null,
      "merged_at": "2026-01-29T14:49:31+00:00",
      "review_cycles": 0,
      "time_to_merge_hours": 0.1,
      "lines_changed": 33,
      "size_bucket": "small"
    },
    {
      "number": 19613,
      "title": "Add logical inset utilities (inset-s, inset-e, inset-bs, inset-be)",
      "classification": "human_save",
      "ci_status": "clean_pass",
      "review_modified": true,
      "escaped": false,
      "escape_reason": "",
      "escape_confidence": null,
      "merged_at": "2026-01-30T14:13:56+00:00",
      "review_cycles": 0,
      "time_to_merge_hours": 23.6,
      "lines_changed": 1300,
      "size_bucket": "large"
    },
    {
      "number": 19612,
      "title": "Add logical sizing utilities (inline-size, block-size)",
      "classification": "human_save",
      "ci_status": "clean_pass",
      "review_modified": true,
      "escaped": false,
      "escape_reason": "",
      "escape_confidence": null,
      "merged_at": "2026-01-30T13:46:37+00:00",
      "review_cycles": 0,
      "time_to_merge_hours": 24.8,
      "lines_changed": 1061,
      "size_bucket": "large"
    },
    {
      "number": 19611,
      "title": "[tailwindcss-vite] Add Register dependency messages logline",
      "classification": "human_save",
      "ci_status": "clean_pass",
      "review_modified": true,
      "escaped": false,
      "escape_reason": "",
      "escape_confidence": null,
      "merged_at": "2026-01-29T14:17:50+00:00",
      "review_cycles": 0,
      "time_to_merge_hours": 2.2,
      "lines_changed": 2,
      "size_bucket": "small"
    },
    {
      "number": 19610,
      "title": "Add @tailwindcss/webpack loader for Tailwind CSS v4",
      "classification": "human_save",
      "ci_status": "clean_pass",
      "review_modified": true,
      "escaped": false,
      "escape_reason": "",
      "escape_confidence": null,
      "merged_at": "2026-01-29T14:16:32+00:00",
      "review_cycles": 1,
      "time_to_merge_hours": 18.5,
      "lines_changed": 1301,
      "size_bucket": "large"
    },
    {
      "number": 19601,
      "title": "Add logical block-start/block-end border, margin, and padding utilities",
      "classification": "human_save",
      "ci_status": "clean_pass",
      "review_modified": true,
      "escaped": false,
      "escape_reason": "",
      "escape_confidence": null,
      "merged_at": "2026-01-30T13:37:51+00:00",
      "review_cycles": 0,
      "time_to_merge_hours": 72.2,
      "lines_changed": 1427,
      "size_bucket": "large"
    },
    {
      "number": 19577,
      "title": "chore: Update outdated GitHub Actions versions",
      "classification": "human_save",
      "ci_status": "clean_pass",
      "review_modified": true,
      "escaped": false,
      "escape_reason": "",
      "escape_confidence": null,
      "merged_at": "2026-02-18T12:27:14+00:00",
      "review_cycles": 0,
      "time_to_merge_hours": 715.8,
      "lines_changed": 6,
      "size_bucket": "small"
    },
    {
      "number": 19525,
      "title": "Fix class extraction for Rails' strict locals",
      "classification": "machine_catch",
      "ci_status": "clean_pass",
      "review_modified": false,
      "escaped": false,
      "escape_reason": "",
      "escape_confidence": null,
      "merged_at": "2026-01-06T11:46:14+00:00",
      "review_cycles": 0,
      "time_to_merge_hours": 16.8,
      "lines_changed": 78,
      "size_bucket": "small"
    },
    {
      "number": 19524,
      "title": "Improve `@utility` name validation",
      "classification": "machine_catch",
      "ci_status": "clean_pass",
      "review_modified": false,
      "escaped": false,
      "escape_reason": "",
      "escape_confidence": null,
      "merged_at": "2026-01-06T11:54:43+00:00",
      "review_cycles": 0,
      "time_to_merge_hours": 18.1,
      "lines_changed": 227,
      "size_bucket": "medium"
    },
    {
      "number": 19493,
      "title": "Fix typo in comment",
      "classification": "human_save",
      "ci_status": "clean_pass",
      "review_modified": true,
      "escaped": false,
      "escape_reason": "",
      "escape_confidence": null,
      "merged_at": "2025-12-27T16:56:29+00:00",
      "review_cycles": 0,
      "time_to_merge_hours": 5.4,
      "lines_changed": 2,
      "size_bucket": "small"
    },
    {
      "number": 19475,
      "title": "chore: fix some typos in comments",
      "classification": "human_save",
      "ci_status": "clean_pass",
      "review_modified": true,
      "escaped": false,
      "escape_reason": "",
      "escape_confidence": null,
      "merged_at": "2025-12-22T13:09:19+00:00",
      "review_cycles": 0,
      "time_to_merge_hours": 5.2,
      "lines_changed": 10,
      "size_bucket": "small"
    },
    {
      "number": 19465,
      "title": "Detect utilities when containing capital letters followed by numbers",
      "classification": "human_save",
      "ci_status": "clean_pass",
      "review_modified": true,
      "escaped": false,
      "escape_reason": "",
      "escape_confidence": null,
      "merged_at": "2025-12-19T10:45:16+00:00",
      "review_cycles": 0,
      "time_to_merge_hours": 9.1,
      "lines_changed": 4,
      "size_bucket": "small"
    },
    {
      "number": 19461,
      "title": "Allow whitespace around `@source inline()` arg",
      "classification": "human_save",
      "ci_status": "clean_pass",
      "review_modified": true,
      "escaped": false,
      "escape_reason": "",
      "escape_confidence": null,
      "merged_at": "2025-12-18T15:51:00+00:00",
      "review_cycles": 1,
      "time_to_merge_hours": 0.3,
      "lines_changed": 41,
      "size_bucket": "small"
    },
    {
      "number": 19457,
      "title": "Clarify the `replaceAlpha` function comment",
      "classification": "human_save",
      "ci_status": "clean_pass",
      "review_modified": true,
      "escaped": false,
      "escape_reason": "",
      "escape_confidence": null,
      "merged_at": "2025-12-18T03:15:42+00:00",
      "review_cycles": 0,
      "time_to_merge_hours": 17.2,
      "lines_changed": 2,
      "size_bucket": "small"
    },
    {
      "number": 19450,
      "title": "Do not wrap `color-mix` in a `@supports` rule if one already exists",
      "classification": "human_save",
      "ci_status": "clean_pass",
      "review_modified": true,
      "escaped": false,
      "escape_reason": "",
      "escape_confidence": null,
      "merged_at": "2025-12-16T21:57:36+00:00",
      "review_cycles": 0,
      "time_to_merge_hours": 8.3,
      "lines_changed": 29,
      "size_bucket": "small"
    },
    {
      "number": 19447,
      "title": "CLI: Emit comment when source maps are saved to files",
      "classification": "machine_catch",
      "ci_status": "clean_pass",
      "review_modified": false,
      "escaped": false,
      "escape_reason": "",
      "escape_confidence": null,
      "merged_at": "2025-12-18T20:02:27+00:00",
      "review_cycles": 0,
      "time_to_merge_hours": 73.8,
      "lines_changed": 38,
      "size_bucket": "small"
    },
    {
      "number": 19436,
      "title": "Fix failing `postcss` integration test",
      "classification": "machine_catch",
      "ci_status": "clean_pass",
      "review_modified": false,
      "escaped": false,
      "escape_reason": "",
      "escape_confidence": null,
      "merged_at": "2025-12-12T14:38:08+00:00",
      "review_cycles": 0,
      "time_to_merge_hours": 0.2,
      "lines_changed": 10,
      "size_bucket": "small"
    },
    {
      "number": 19431,
      "title": "Release v4.1.18",
      "classification": "human_save",
      "ci_status": "clean_pass",
      "review_modified": true,
      "escaped": false,
      "escape_reason": "",
      "escape_confidence": null,
      "merged_at": "2025-12-11T15:55:26+00:00",
      "review_cycles": 0,
      "time_to_merge_hours": 21.1,
      "lines_changed": 80,
      "size_bucket": "small"
    },
    {
      "number": 19429,
      "title": "Fix provenance setup for v3",
      "classification": "human_save",
      "ci_status": "clean_pass",
      "review_modified": true,
      "escaped": false,
      "escape_reason": "",
      "escape_confidence": null,
      "merged_at": "2025-12-09T17:19:22+00:00",
      "review_cycles": 0,
      "time_to_merge_hours": 0.3,
      "lines_changed": 8,
      "size_bucket": "small"
    },
    {
      "number": 19421,
      "title": "Don\u2019t try reading from pipes or special file descriptors",
      "classification": "human_save",
      "ci_status": "clean_pass",
      "review_modified": true,
      "escaped": false,
      "escape_reason": "",
      "escape_confidence": null,
      "merged_at": "2025-12-08T22:04:51+00:00",
      "review_cycles": 0,
      "time_to_merge_hours": 0.2,
      "lines_changed": 18,
      "size_bucket": "small"
    },
    {
      "number": 19419,
      "title": "Don\u2019t emit color-mix fallback rules inside `@keyframes`",
      "classification": "human_save",
      "ci_status": "clean_pass",
      "review_modified": true,
      "escaped": false,
      "escape_reason": "",
      "escape_confidence": null,
      "merged_at": "2025-12-08T14:40:16+00:00",
      "review_cycles": 0,
      "time_to_merge_hours": 0.1,
      "lines_changed": 42,
      "size_bucket": "small"
    },
    {
      "number": 19416,
      "title": "Only use the last value when parsing duplicate cli arguments",
      "classification": "human_save",
      "ci_status": "clean_pass",
      "review_modified": true,
      "escaped": false,
      "escape_reason": "",
      "escape_confidence": null,
      "merged_at": "2025-12-07T17:26:22+00:00",
      "review_cycles": 0,
      "time_to_merge_hours": 4.0,
      "lines_changed": 45,
      "size_bucket": "small"
    },
    {
      "number": 19407,
      "title": "Fix formatting of path in README.md",
      "classification": "ungated",
      "ci_status": "no_checks",
      "review_modified": false,
      "escaped": false,
      "escape_reason": "",
      "escape_confidence": null,
      "merged_at": "2025-12-04T13:25:51+00:00",
      "review_cycles": 0,
      "time_to_merge_hours": 3.7,
      "lines_changed": 2,
      "size_bucket": "small"
    },
    {
      "number": 19405,
      "title": "Expose `candidatesToAst` to the language server ",
      "classification": "human_save",
      "ci_status": "clean_pass",
      "review_modified": true,
      "escaped": false,
      "escape_reason": "",
      "escape_confidence": null,
      "merged_at": "2025-12-08T15:54:42+00:00",
      "review_cycles": 0,
      "time_to_merge_hours": 112.0,
      "lines_changed": 103,
      "size_bucket": "medium"
    },
    {
      "number": 19400,
      "title": "Fix invalid template tags in tests",
      "classification": "human_save",
      "ci_status": "clean_pass",
      "review_modified": true,
      "escaped": false,
      "escape_reason": "",
      "escape_confidence": null,
      "merged_at": "2025-12-02T19:51:21+00:00",
      "review_cycles": 1,
      "time_to_merge_hours": 1.5,
      "lines_changed": 11,
      "size_bucket": "small"
    },
    {
      "number": 19397,
      "title": "Validate named values in candidate parser",
      "classification": "machine_catch",
      "ci_status": "clean_pass",
      "review_modified": false,
      "escaped": false,
      "escape_reason": "",
      "escape_confidence": null,
      "merged_at": "2025-12-03T20:06:25+00:00",
      "review_cycles": 0,
      "time_to_merge_hours": 51.9,
      "lines_changed": 15,
      "size_bucket": "small"
    },
    {
      "number": 19396,
      "title": "Canonicalization: combine `text-*` and `leading-*` classes",
      "classification": "human_save",
      "ci_status": "clean_pass",
      "review_modified": true,
      "escaped": false,
      "escape_reason": "",
      "escape_confidence": null,
      "merged_at": "2025-12-01T15:01:24+00:00",
      "review_cycles": 0,
      "time_to_merge_hours": 2.9,
      "lines_changed": 272,
      "size_bucket": "medium"
    },
    {
      "number": 19391,
      "title": "Don't inline all env vars in Standalone CLI",
      "classification": "human_save",
      "ci_status": "clean_pass",
      "review_modified": true,
      "escaped": false,
      "escape_reason": "",
      "escape_confidence": null,
      "merged_at": "2025-12-08T16:23:20+00:00",
      "review_cycles": 0,
      "time_to_merge_hours": 194.6,
      "lines_changed": 180,
      "size_bucket": "medium"
    },
    {
      "number": 19381,
      "title": "Handle backwards compatibility for `content` theme from JS configs",
      "classification": "human_save",
      "ci_status": "clean_pass",
      "review_modified": true,
      "escaped": false,
      "escape_reason": "",
      "escape_confidence": null,
      "merged_at": "2025-11-29T16:19:37+00:00",
      "review_cycles": 1,
      "time_to_merge_hours": 75.2,
      "lines_changed": 26,
      "size_bucket": "small"
    },
    {
      "number": 19379,
      "title": "Try to canonicalize any arbitrary utility to a bare value",
      "classification": "human_save",
      "ci_status": "clean_pass",
      "review_modified": true,
      "escaped": false,
      "escape_reason": "",
      "escape_confidence": null,
      "merged_at": "2025-11-26T11:07:21+00:00",
      "review_cycles": 0,
      "time_to_merge_hours": 0.4,
      "lines_changed": 56,
      "size_bucket": "small"
    },
    {
      "number": 19373,
      "title": "Fix source map generation during when watching files on the CLI",
      "classification": "machine_catch",
      "ci_status": "clean_pass",
      "review_modified": false,
      "escaped": false,
      "escape_reason": "",
      "escape_confidence": null,
      "merged_at": "2025-11-25T17:22:58+00:00",
      "review_cycles": 0,
      "time_to_merge_hours": 2.3,
      "lines_changed": 482,
      "size_bucket": "medium"
    },
    {
      "number": 19348,
      "title": "Improve compatibility with special default values in JS configs",
      "classification": "human_save",
      "ci_status": "clean_pass",
      "review_modified": true,
      "escaped": false,
      "escape_reason": "",
      "escape_confidence": null,
      "merged_at": "2025-11-28T20:45:10+00:00",
      "review_cycles": 1,
      "time_to_merge_hours": 189.0,
      "lines_changed": 124,
      "size_bucket": "medium"
    },
    {
      "number": 19344,
      "title": "Handle `future` and `experimental` config keys during upgrade",
      "classification": "human_save",
      "ci_status": "clean_pass",
      "review_modified": true,
      "escaped": false,
      "escape_reason": "",
      "escape_confidence": null,
      "merged_at": "2025-11-20T22:11:43+00:00",
      "review_cycles": 0,
      "time_to_merge_hours": 0.5,
      "lines_changed": 276,
      "size_bucket": "medium"
    },
    {
      "number": 19337,
      "title": "Don\u2019t unconditionally convert config keys to `kebab-case`",
      "classification": "human_save",
      "ci_status": "clean_pass",
      "review_modified": true,
      "escaped": false,
      "escape_reason": "",
      "escape_confidence": null,
      "merged_at": "2025-11-20T22:39:55+00:00",
      "review_cycles": 0,
      "time_to_merge_hours": 25.7,
      "lines_changed": 95,
      "size_bucket": "small"
    },
    {
      "number": 19335,
      "title": "v3: Don\u2019t break `sibling-*()` functions when used inside `calc(\u2026)`",
      "classification": "human_save",
      "ci_status": "clean_pass",
      "review_modified": true,
      "escaped": false,
      "escape_reason": "",
      "escape_confidence": null,
      "merged_at": "2025-11-19T15:35:48+00:00",
      "review_cycles": 0,
      "time_to_merge_hours": 1.8,
      "lines_changed": 336,
      "size_bucket": "medium"
    },
    {
      "number": 19308,
      "title": "perf(vite): add plugin hook filter",
      "classification": "human_save",
      "ci_status": "clean_pass",
      "review_modified": true,
      "escaped": false,
      "escape_reason": "",
      "escape_confidence": null,
      "merged_at": "2025-11-14T15:44:07+00:00",
      "review_cycles": 1,
      "time_to_merge_hours": 0.9,
      "lines_changed": 83,
      "size_bucket": "small"
    },
    {
      "number": 19282,
      "title": "Include filename and line numbers in CSS parse errors",
      "classification": "human_save",
      "ci_status": "clean_pass",
      "review_modified": true,
      "escaped": false,
      "escape_reason": "",
      "escape_confidence": null,
      "merged_at": "2025-11-10T18:29:23+00:00",
      "review_cycles": 1,
      "time_to_merge_hours": 58.1,
      "lines_changed": 206,
      "size_bucket": "medium"
    },
    {
      "number": 19274,
      "title": "Fix validation of `source(\u2026)` paths",
      "classification": "human_save",
      "ci_status": "clean_pass",
      "review_modified": true,
      "escaped": false,
      "escape_reason": "",
      "escape_confidence": null,
      "merged_at": "2025-11-06T21:24:18+00:00",
      "review_cycles": 0,
      "time_to_merge_hours": 4.0,
      "lines_changed": 230,
      "size_bucket": "medium"
    },
    {
      "number": 19272,
      "title": "Release v4.1.17",
      "classification": "human_save",
      "ci_status": "clean_pass",
      "review_modified": true,
      "escaped": false,
      "escape_reason": "",
      "escape_confidence": null,
      "merged_at": "2025-11-06T15:20:36+00:00",
      "review_cycles": 0,
      "time_to_merge_hours": 1.0,
      "lines_changed": 58,
      "size_bucket": "small"
    },
    {
      "number": 19263,
      "title": "Substitute `@variant` inside utilities",
      "classification": "human_save",
      "ci_status": "clean_pass",
      "review_modified": true,
      "escaped": false,
      "escape_reason": "",
      "escape_confidence": null,
      "merged_at": "2025-11-04T16:28:53+00:00",
      "review_cycles": 0,
      "time_to_merge_hours": 0.6,
      "lines_changed": 74,
      "size_bucket": "small"
    },
    {
      "number": 19256,
      "title": "Remove unused `crossbeam` dependency in oxide",
      "classification": "human_save",
      "ci_status": "clean_pass",
      "review_modified": true,
      "escaped": false,
      "escape_reason": "",
      "escape_confidence": null,
      "merged_at": "2025-11-04T15:37:21+00:00",
      "review_cycles": 0,
      "time_to_merge_hours": 17.9,
      "lines_changed": 24,
      "size_bucket": "small"
    },
    {
      "number": 19243,
      "title": "Skip comments in Ruby files when checking for class names",
      "classification": "human_save",
      "ci_status": "clean_pass",
      "review_modified": true,
      "escaped": false,
      "escape_reason": "",
      "escape_confidence": null,
      "merged_at": "2025-11-13T10:53:39+00:00",
      "review_cycles": 1,
      "time_to_merge_hours": 306.2,
      "lines_changed": 142,
      "size_bucket": "medium"
    },
    {
      "number": 19185,
      "title": "Release 4.1.16",
      "classification": "human_save",
      "ci_status": "clean_pass",
      "review_modified": true,
      "escaped": false,
      "escape_reason": "",
      "escape_confidence": null,
      "merged_at": "2025-10-23T10:32:28+00:00",
      "review_cycles": 0,
      "time_to_merge_hours": 0.4,
      "lines_changed": 49,
      "size_bucket": "small"
    },
    {
      "number": 19184,
      "title": "Fix incorrect colors used in pseudo-element",
      "classification": "human_save",
      "ci_status": "clean_pass",
      "review_modified": true,
      "escaped": false,
      "escape_reason": "",
      "escape_confidence": null,
      "merged_at": "2025-10-23T10:07:02+00:00",
      "review_cycles": 0,
      "time_to_merge_hours": 0.5,
      "lines_changed": 87,
      "size_bucket": "small"
    },
    {
      "number": 19178,
      "title": "Improve canonicalization for `& > :pseudo` and `& :pseudo` arbitrary variants",
      "classification": "human_save",
      "ci_status": "clean_pass",
      "review_modified": true,
      "escaped": false,
      "escape_reason": "",
      "escape_confidence": null,
      "merged_at": "2025-10-22T12:29:08+00:00",
      "review_cycles": 0,
      "time_to_merge_hours": 0.8,
      "lines_changed": 27,
      "size_bucket": "small"
    },
    {
      "number": 19176,
      "title": "Fix canonicalization of arbitrary variants with attribute selectors",
      "classification": "human_save",
      "ci_status": "clean_pass",
      "review_modified": true,
      "escaped": false,
      "escape_reason": "",
      "escape_confidence": null,
      "merged_at": "2025-10-22T12:19:55+00:00",
      "review_cycles": 0,
      "time_to_merge_hours": 1.2,
      "lines_changed": 17,
      "size_bucket": "small"
    },
    {
      "number": 19172,
      "title": "Discard candidates with an empty data type",
      "classification": "human_save",
      "ci_status": "clean_pass",
      "review_modified": true,
      "escaped": false,
      "escape_reason": "",
      "escape_confidence": null,
      "merged_at": "2025-10-22T10:14:43+00:00",
      "review_cycles": 0,
      "time_to_merge_hours": 14.0,
      "lines_changed": 16,
      "size_bucket": "small"
    },
    {
      "number": 19171,
      "title": "Improve memory usage during canonicalization",
      "classification": "human_save",
      "ci_status": "clean_pass",
      "review_modified": true,
      "escaped": false,
      "escape_reason": "",
      "escape_confidence": null,
      "merged_at": "2025-10-21T14:55:31+00:00",
      "review_cycles": 0,
      "time_to_merge_hours": 0.9,
      "lines_changed": 1511,
      "size_bucket": "large"
    },
    {
      "number": 19169,
      "title": "Stop suggesting legacy utilities",
      "classification": "human_save",
      "ci_status": "clean_pass",
      "review_modified": true,
      "escaped": false,
      "escape_reason": "",
      "escape_confidence": null,
      "merged_at": "2025-10-21T10:54:11+00:00",
      "review_cycles": 0,
      "time_to_merge_hours": 11.2,
      "lines_changed": 110,
      "size_bucket": "medium"
    },
    {
      "number": 19159,
      "title": "Release 4.1.15",
      "classification": "human_save",
      "ci_status": "clean_pass",
      "review_modified": true,
      "escaped": false,
      "escape_reason": "",
      "escape_confidence": null,
      "merged_at": "2025-10-20T12:48:42+00:00",
      "review_cycles": 0,
      "time_to_merge_hours": 0.2,
      "lines_changed": 57,
      "size_bucket": "small"
    },
    {
      "number": 19157,
      "title": "Mark `break-words` as deprecated, and upgrade to `wrap-break-word`",
      "classification": "human_save",
      "ci_status": "clean_pass",
      "review_modified": true,
      "escaped": false,
      "escape_reason": "",
      "escape_confidence": null,
      "merged_at": "2025-10-20T12:14:25+00:00",
      "review_cycles": 0,
      "time_to_merge_hours": 1.0,
      "lines_changed": 35,
      "size_bucket": "small"
    },
    {
      "number": 19156,
      "title": "Ignore `--tw-` variables during internal signature computation",
      "classification": "human_save",
      "ci_status": "clean_pass",
      "review_modified": true,
      "escaped": false,
      "escape_reason": "",
      "escape_confidence": null,
      "merged_at": "2025-10-20T15:21:07+00:00",
      "review_cycles": 0,
      "time_to_merge_hours": 4.4,
      "lines_changed": 40,
      "size_bucket": "small"
    },
    {
      "number": 19155,
      "title": "Revert agentic issue-triage workflow",
      "classification": "human_save",
      "ci_status": "failed",
      "review_modified": true,
      "escaped": false,
      "escape_reason": "",
      "escape_confidence": null,
      "merged_at": "2025-10-20T10:20:08+00:00",
      "review_cycles": 0,
      "time_to_merge_hours": 0.6,
      "lines_changed": 3402,
      "size_bucket": "large"
    },
    {
      "number": 19149,
      "title": "Remove Oxide postinstall script",
      "classification": "human_save",
      "ci_status": "clean_pass",
      "review_modified": true,
      "escaped": false,
      "escape_reason": "",
      "escape_confidence": null,
      "merged_at": "2025-10-19T08:50:21+00:00",
      "review_cycles": 1,
      "time_to_merge_hours": 0.1,
      "lines_changed": 297,
      "size_bucket": "medium"
    },
    {
      "number": 19148,
      "title": "Incorporate changes from latest `ignore` crate",
      "classification": "human_save",
      "ci_status": "clean_pass",
      "review_modified": true,
      "escaped": false,
      "escape_reason": "",
      "escape_confidence": null,
      "merged_at": "2025-10-20T13:49:40+00:00",
      "review_cycles": 1,
      "time_to_merge_hours": 44.3,
      "lines_changed": 521,
      "size_bucket": "large"
    },
    {
      "number": 19147,
      "title": "Collapse multiple utilities",
      "classification": "human_save",
      "ci_status": "clean_pass",
      "review_modified": true,
      "escaped": false,
      "escape_reason": "",
      "escape_confidence": null,
      "merged_at": "2025-10-20T15:15:31+00:00",
      "review_cycles": 0,
      "time_to_merge_hours": 61.9,
      "lines_changed": 1082,
      "size_bucket": "large"
    },
    {
      "number": 19143,
      "title": "Update Lightning CSS to 1.30.2",
      "classification": "human_save",
      "ci_status": "clean_pass",
      "review_modified": true,
      "escaped": false,
      "escape_reason": "",
      "escape_confidence": null,
      "merged_at": "2025-10-17T19:41:49+00:00",
      "review_cycles": 0,
      "time_to_merge_hours": 0.6,
      "lines_changed": 216,
      "size_bucket": "medium"
    },
    {
      "number": 19131,
      "title": "Add `optimize` option to `@tailwindcss/vite` plugin",
      "classification": "human_save",
      "ci_status": "clean_pass",
      "review_modified": true,
      "escaped": false,
      "escape_reason": "",
      "escape_confidence": null,
      "merged_at": "2025-10-17T15:00:25+00:00",
      "review_cycles": 0,
      "time_to_merge_hours": 44.3,
      "lines_changed": 191,
      "size_bucket": "medium"
    },
    {
      "number": 19130,
      "title": "Fix parsing issue when `\\t` is used in at-rules",
      "classification": "human_save",
      "ci_status": "clean_pass",
      "review_modified": true,
      "escaped": false,
      "escape_reason": "",
      "escape_confidence": null,
      "merged_at": "2025-10-15T09:50:02+00:00",
      "review_cycles": 0,
      "time_to_merge_hours": 1.2,
      "lines_changed": 23,
      "size_bucket": "small"
    },
    {
      "number": 19126,
      "title": "Generalize the `walk` implementation",
      "classification": "human_save",
      "ci_status": "clean_pass",
      "review_modified": true,
      "escaped": false,
      "escape_reason": "",
      "escape_confidence": null,
      "merged_at": "2025-10-15T19:28:13+00:00",
      "review_cycles": 1,
      "time_to_merge_hours": 22.4,
      "lines_changed": 2905,
      "size_bucket": "large"
    },
    {
      "number": 19124,
      "title": "Make TypeScript a bit more happy",
      "classification": "human_save",
      "ci_status": "clean_pass",
      "review_modified": true,
      "escaped": false,
      "escape_reason": "",
      "escape_confidence": null,
      "merged_at": "2025-10-14T19:52:47+00:00",
      "review_cycles": 0,
      "time_to_merge_hours": 0.5,
      "lines_changed": 94,
      "size_bucket": "small"
    },
    {
      "number": 19111,
      "title": "Don\u2019t index into strings with the `theme(\u2026)` function",
      "classification": "human_save",
      "ci_status": "clean_pass",
      "review_modified": true,
      "escaped": false,
      "escape_reason": "",
      "escape_confidence": null,
      "merged_at": "2025-10-13T15:44:33+00:00",
      "review_cycles": 0,
      "time_to_merge_hours": 1.3,
      "lines_changed": 38,
      "size_bucket": "small"
    },
    {
      "number": 19110,
      "title": "Clone AST nodes used in `staticValues`",
      "classification": "human_save",
      "ci_status": "clean_pass",
      "review_modified": true,
      "escaped": false,
      "escape_reason": "",
      "escape_confidence": null,
      "merged_at": "2025-10-13T14:23:10+00:00",
      "review_cycles": 0,
      "time_to_merge_hours": 1.0,
      "lines_changed": 47,
      "size_bucket": "small"
    },
    {
      "number": 19101,
      "title": "Canonicalize dimensions",
      "classification": "human_save",
      "ci_status": "clean_pass",
      "review_modified": true,
      "escaped": false,
      "escape_reason": "",
      "escape_confidence": null,
      "merged_at": "2025-10-10T15:44:53+00:00",
      "review_cycles": 0,
      "time_to_merge_hours": 1.9,
      "lines_changed": 390,
      "size_bucket": "medium"
    },
    {
      "number": 19100,
      "title": "Move modifier of `not-*`, `has-*`, and `in-*` variant to sub variant",
      "classification": "human_save",
      "ci_status": "clean_pass",
      "review_modified": true,
      "escaped": false,
      "escape_reason": "",
      "escape_confidence": null,
      "merged_at": "2025-10-09T17:30:01+00:00",
      "review_cycles": 1,
      "time_to_merge_hours": 0.8,
      "lines_changed": 33,
      "size_bucket": "small"
    },
    {
      "number": 19097,
      "title": "Fix resolving colors via `theme(\u2026)` in compat mode with nested objects",
      "classification": "human_save",
      "ci_status": "clean_pass",
      "review_modified": true,
      "escaped": false,
      "escape_reason": "",
      "escape_confidence": null,
      "merged_at": "2025-10-09T17:10:32+00:00",
      "review_cycles": 1,
      "time_to_merge_hours": 3.2,
      "lines_changed": 103,
      "size_bucket": "medium"
    },
    {
      "number": 19095,
      "title": "Canonicalization constant folding and handling zeros",
      "classification": "human_save",
      "ci_status": "clean_pass",
      "review_modified": true,
      "escaped": false,
      "escape_reason": "",
      "escape_confidence": null,
      "merged_at": "2025-10-09T18:09:29+00:00",
      "review_cycles": 1,
      "time_to_merge_hours": 7.1,
      "lines_changed": 417,
      "size_bucket": "medium"
    },
    {
      "number": 19094,
      "title": "Suppress warnings when using `:deep`, `:slotted` and `:global`",
      "classification": "human_save",
      "ci_status": "clean_pass",
      "review_modified": true,
      "escaped": false,
      "escape_reason": "",
      "escape_confidence": null,
      "merged_at": "2025-10-09T09:58:51+00:00",
      "review_cycles": 0,
      "time_to_merge_hours": 0.1,
      "lines_changed": 12,
      "size_bucket": "small"
    },
    {
      "number": 19072,
      "title": "Improve percentage canonicalization",
      "classification": "human_save",
      "ci_status": "clean_pass",
      "review_modified": true,
      "escaped": false,
      "escape_reason": "",
      "escape_confidence": null,
      "merged_at": "2025-10-07T13:47:22+00:00",
      "review_cycles": 0,
      "time_to_merge_hours": 0.2,
      "lines_changed": 23,
      "size_bucket": "small"
    },
    {
      "number": 19069,
      "title": "Fix Safari devtools issues because of nested `@supports` at-rules without normal `rule`",
      "classification": "human_save",
      "ci_status": "clean_pass",
      "review_modified": true,
      "escaped": false,
      "escape_reason": "",
      "escape_confidence": null,
      "merged_at": "2025-10-06T18:04:40+00:00",
      "review_cycles": 0,
      "time_to_merge_hours": 0.7,
      "lines_changed": 82,
      "size_bucket": "small"
    },
    {
      "number": 19068,
      "title": "Fix failing integration tests",
      "classification": "human_save",
      "ci_status": "clean_pass",
      "review_modified": true,
      "escaped": false,
      "escape_reason": "",
      "escape_confidence": null,
      "merged_at": "2025-10-06T15:46:25+00:00",
      "review_cycles": 0,
      "time_to_merge_hours": 0.1,
      "lines_changed": 5,
      "size_bucket": "small"
    },
    {
      "number": 19067,
      "title": "Improve performance of cloning AST nodes",
      "classification": "human_save",
      "ci_status": "clean_pass",
      "review_modified": true,
      "escaped": false,
      "escape_reason": "",
      "escape_confidence": null,
      "merged_at": "2025-10-07T10:46:37+00:00",
      "review_cycles": 0,
      "time_to_merge_hours": 19.8,
      "lines_changed": 349,
      "size_bucket": "medium"
    },
    {
      "number": 19059,
      "title": "Introduce `canonicalizeCandidates` on the internal Design System",
      "classification": "human_save",
      "ci_status": "clean_pass",
      "review_modified": true,
      "escaped": false,
      "escape_reason": "",
      "escape_confidence": null,
      "merged_at": "2025-10-07T10:41:12+00:00",
      "review_cycles": 1,
      "time_to_merge_hours": 24.8,
      "lines_changed": 5436,
      "size_bucket": "large"
    },
    {
      "number": 19057,
      "title": "Add agentic workflow issue-triage",
      "classification": "human_save",
      "ci_status": "clean_pass",
      "review_modified": true,
      "escaped": false,
      "escape_reason": "",
      "escape_confidence": null,
      "merged_at": "2025-10-06T10:24:51+00:00",
      "review_cycles": 0,
      "time_to_merge_hours": 1.2,
      "lines_changed": 3392,
      "size_bucket": "large"
    },
    {
      "number": 19043,
      "title": "Never publish v3 as `latest` on npm",
      "classification": "human_save",
      "ci_status": "failed",
      "review_modified": true,
      "escaped": false,
      "escape_reason": "",
      "escape_confidence": null,
      "merged_at": "2025-10-01T16:25:46+00:00",
      "review_cycles": 0,
      "time_to_merge_hours": 0.0,
      "lines_changed": 2,
      "size_bucket": "small"
    },
    {
      "number": 19042,
      "title": "v3: Bundle postcss-load-config v4 with the standalone CLI",
      "classification": "human_save",
      "ci_status": "clean_pass",
      "review_modified": true,
      "escaped": false,
      "escape_reason": "",
      "escape_confidence": null,
      "merged_at": "2025-10-01T15:18:15+00:00",
      "review_cycles": 0,
      "time_to_merge_hours": 0.1,
      "lines_changed": 91,
      "size_bucket": "small"
    },
    {
      "number": 19038,
      "title": "Prepare v3.4.18 release",
      "classification": "human_save",
      "ci_status": "clean_pass",
      "review_modified": true,
      "escaped": false,
      "escape_reason": "",
      "escape_confidence": null,
      "merged_at": "2025-10-01T13:45:30+00:00",
      "review_cycles": 0,
      "time_to_merge_hours": 17.0,
      "lines_changed": 23,
      "size_bucket": "small"
    },
    {
      "number": 19037,
      "title": "Prepare v4.1.14 release",
      "classification": "human_save",
      "ci_status": "clean_pass",
      "review_modified": true,
      "escaped": false,
      "escape_reason": "",
      "escape_confidence": null,
      "merged_at": "2025-10-01T15:48:02+00:00",
      "review_cycles": 0,
      "time_to_merge_hours": 19.0,
      "lines_changed": 124,
      "size_bucket": "medium"
    },
    {
      "number": 19031,
      "title": "Ensure first class inside className in React is migrated",
      "classification": "human_save",
      "ci_status": "clean_pass",
      "review_modified": true,
      "escaped": false,
      "escape_reason": "",
      "escape_confidence": null,
      "merged_at": "2025-09-30T15:13:14+00:00",
      "review_cycles": 0,
      "time_to_merge_hours": 16.5,
      "lines_changed": 37,
      "size_bucket": "small"
    },
    {
      "number": 19030,
      "title": "v3: Remove irrelevant utility rules when matching important classes",
      "classification": "human_save",
      "ci_status": "clean_pass",
      "review_modified": true,
      "escaped": false,
      "escape_reason": "",
      "escape_confidence": null,
      "merged_at": "2025-09-29T22:11:09+00:00",
      "review_cycles": 0,
      "time_to_merge_hours": 2.1,
      "lines_changed": 159,
      "size_bucket": "medium"
    },
    {
      "number": 19028,
      "title": "Show version mismatch when running upgrade tool",
      "classification": "human_save",
      "ci_status": "clean_pass",
      "review_modified": true,
      "escaped": false,
      "escape_reason": "",
      "escape_confidence": null,
      "merged_at": "2025-09-29T14:21:44+00:00",
      "review_cycles": 1,
      "time_to_merge_hours": 2.9,
      "lines_changed": 291,
      "size_bucket": "medium"
    },
    {
      "number": 19026,
      "title": "Add `Upgrading from Tailwind CSS v\u2026` when running upgrade tool",
      "classification": "human_save",
      "ci_status": "clean_pass",
      "review_modified": true,
      "escaped": false,
      "escape_reason": "",
      "escape_confidence": null,
      "merged_at": "2025-09-29T13:59:55+00:00",
      "review_cycles": 0,
      "time_to_merge_hours": 4.3,
      "lines_changed": 67,
      "size_bucket": "small"
    },
    {
      "number": 18970,
      "title": "Support Vite Environment API",
      "classification": "machine_catch",
      "ci_status": "clean_pass",
      "review_modified": false,
      "escaped": false,
      "escape_reason": "",
      "escape_confidence": null,
      "merged_at": "2025-11-18T17:38:57+00:00",
      "review_cycles": 0,
      "time_to_merge_hours": 1437.4,
      "lines_changed": 144,
      "size_bucket": "medium"
    },
    {
      "number": 4044,
      "title": "use href to get the full path of the file",
      "classification": "ungated",
      "ci_status": "no_checks",
      "review_modified": false,
      "escaped": false,
      "escape_reason": "",
      "escape_confidence": null,
      "merged_at": "2021-05-07T18:48:09+00:00",
      "review_cycles": 1,
      "time_to_merge_hours": 622.0,
      "lines_changed": 3,
      "size_bucket": "small"
    },
    {
      "number": 4272,
      "title": "[JIT] Add support for \"raw\" purge content",
      "classification": "ungated",
      "ci_status": "no_checks",
      "review_modified": false,
      "escaped": false,
      "escape_reason": "",
      "escape_confidence": null,
      "merged_at": "2021-05-07T12:58:58+00:00",
      "review_cycles": 0,
      "time_to_merge_hours": 1.4,
      "lines_changed": 1017,
      "size_bucket": "large"
    },
    {
      "number": 19862,
      "title": "Use `json` preprocessor for new-line delimited JSON files",
      "classification": "pending",
      "ci_status": "clean_pass",
      "review_modified": false,
      "escaped": false,
      "escape_reason": "",
      "escape_confidence": null,
      "merged_at": "2026-03-26T22:42:03+00:00",
      "review_cycles": 0,
      "time_to_merge_hours": 6.2,
      "lines_changed": 3,
      "size_bucket": "small"
    },
    {
      "number": 19858,
      "title": "Canonicalize negative arbitrary values",
      "classification": "pending",
      "ci_status": "clean_pass",
      "review_modified": false,
      "escaped": false,
      "escape_reason": "",
      "escape_confidence": null,
      "merged_at": "2026-03-26T13:44:09+00:00",
      "review_cycles": 0,
      "time_to_merge_hours": 0.4,
      "lines_changed": 460,
      "size_bucket": "medium"
    }
  ],
  "effectiveness": {
    "median_review_cycles": 0,
    "median_ttm_hours": 3.2,
    "by_classification": {
      "machine_catch": {
        "median_review_cycles": 0.0,
        "median_ttm_hours": 0.8
      },
      "human_save": {
        "median_review_cycles": 0,
        "median_ttm_hours": 4.4
      },
      "escape": {
        "median_review_cycles": 0.0,
        "median_ttm_hours": 0.0
      }
    },
    "by_size": {
      "small": {
        "count": 75,
        "median_review_cycles": 0,
        "median_ttm_hours": 1.2,
        "machine_catch_rate": 0.24,
        "human_save_rate": 0.76,
        "escape_rate": 0.0
      },
      "medium": {
        "count": 28,
        "median_review_cycles": 0.0,
        "median_ttm_hours": 18.6,
        "machine_catch_rate": 0.1071,
        "human_save_rate": 0.8929,
        "escape_rate": 0.0
      },
      "large": {
        "count": 14,
        "median_review_cycles": 0.0,
        "median_ttm_hours": 23.0,
        "machine_catch_rate": 0.2143,
        "human_save_rate": 0.7857,
        "escape_rate": 0.0
      }
    }
  }
}